odoo/addons/mrp_unbuild_move_link/README.rst
odoo/addons/mrp_unbuild_move_link/__init__.py
odoo/addons/mrp_unbuild_move_link/__manifest__.py
odoo/addons/mrp_unbuild_move_link/i18n/es.po
odoo/addons/mrp_unbuild_move_link/i18n/it.po
odoo/addons/mrp_unbuild_move_link/i18n/mrp_unbuild_move_link.pot
odoo/addons/mrp_unbuild_move_link/models/__init__.py
odoo/addons/mrp_unbuild_move_link/models/mrp_unbuild.py
odoo/addons/mrp_unbuild_move_link/models/stock_move.py
odoo/addons/mrp_unbuild_move_link/readme/CONTRIBUTORS.rst
odoo/addons/mrp_unbuild_move_link/readme/DESCRIPTION.rst
odoo/addons/mrp_unbuild_move_link/static/description/icon.png
odoo/addons/mrp_unbuild_move_link/static/description/index.html
odoo/addons/mrp_unbuild_move_link/tests/__init__.py
odoo/addons/mrp_unbuild_move_link/tests/test_mrp_unbuild_move_link.py
odoo/addons/mrp_unbuild_move_link/views/stock_move_views.xml
odoo14_addon_mrp_unbuild_move_link-14.0.1.0.1.dev8.dist-info/METADATA
odoo14_addon_mrp_unbuild_move_link-14.0.1.0.1.dev8.dist-info/WHEEL
odoo14_addon_mrp_unbuild_move_link-14.0.1.0.1.dev8.dist-info/top_level.txt
odoo14_addon_mrp_unbuild_move_link-14.0.1.0.1.dev8.dist-info/RECORD
