Metadata-Version: 2.1
Name: odoo14-addon-mrp_unbuild_move_link
Version: 14.0.1.0.1.dev8
Summary: Link the stock moves of manufacturing orders to the respective unbuild orders
Home-page: https://github.com/OCA/manufacture
Author: ForgeFlow, Odoo Community Association (OCA)
Author-email: support@odoo-community.org
License: LGPL-3
Classifier: Programming Language :: Python
Classifier: Framework :: Odoo
Classifier: Framework :: Odoo :: 14.0
Classifier: License :: OSI Approved :: GNU Lesser General Public License v3 (LGPLv3)
Requires-Python: >=3.6
Requires-Dist: odoo<14.1dev,>=14.0a
